{
  "date": "2026-03-27",
  "lastUpdate": "2026年3月27日 16:34",
  "todayUpdates": 100,
  "versionUpdate": {
    "title": "2026年春季赛季更新 - 新增UT赛季球员卡",
    "date": "2026年3月25日",
    "maintenanceTime": "3月25日 08:00（预计停服3小时）",
    "content": [
      "新增UT赛季球员卡系统，包含大量现役和传奇球星",
      "优化比赛引擎，提升球员AI和战术响应速度",
      "新增战术板预设功能，可保存多套战术配置",
      "俱乐部系统更新，新增俱乐部联赛和奖励机制",
      "转会市场优化，新增球员筛选和价格预警功能",
      "挑战赛新增困难难度，奖励大幅提升",
      "球员培养系统优化，升级成功率提升10%",
      "活动系统更新，新增限时球员包和特殊活动",
      "修复了部分球员卡显示异常的bug",
      "优化了网络连接，提升游戏稳定性"
    ]
  },
  "douyin": {
    "platform": "抖音",
    "items": [
      {
        "title": "球员卡对比评测",
        "description": "不同球员卡对比、强度分析、适用场景",
        "time": "2026年3月4日"
      },
      {
        "title": "球员合成技巧",
        "description": "合成规则、成功率提升、优质球员获取",
        "time": "2026年3月4日"
      },
      {
        "title": "球员交易市场分析",
        "description": "市场趋势、球员价格、投资建议",
        "time": "2026年3月7日"
      },
      {
        "title": "比赛教学",
        "description": "进攻技巧、防守技巧、战术运用",
        "time": "2026年3月1日"
      },
      {
        "title": "FC足球世界新手攻略",
        "description": "新手入门指南、基础操作、快速升级攻略",
        "time": "2026年3月19日"
      },
      {
        "title": "挑战赛通关攻略",
        "description": "挑战赛难度、通关技巧、奖励分析",
        "time": "2026年3月15日"
      },
      {
        "title": "UT模式最强球员推荐",
        "description": "当前版本UT模式强势球员、性价比球员推荐",
        "time": "2026年3月3日"
      },
      {
        "title": "球员属性解读",
        "description": "球员属性详解、关键属性、培养方向",
        "time": "2026年3月11日"
      },
      {
        "title": "阵容搭配推荐",
        "description": "不同阵型、球员组合、战术配合",
        "time": "2026年3月10日"
      },
      {
        "title": "比赛节奏控制",
        "description": "节奏把握、战术调整、关键时刻处理",
        "time": "2026年2月28日"
      },
      {
        "title": "防守战术详解",
        "description": "防守阵型、球员防守、区域防守",
        "time": "2026年2月27日"
      },
      {
        "title": "俱乐部运营攻略",
        "description": "俱乐部管理、成员招募、活动组织",
        "time": "2026年3月6日"
      },
      {
        "title": "特殊球员卡获取",
        "description": "限定卡、特殊卡获取途径、活动攻略",
        "time": "2026年3月16日"
      },
      {
        "title": "战术板设置教学",
        "description": "战术板配置、阵型选择、球员站位",
        "time": "2026年3月25日"
      },
      {
        "title": "FC足球世界赛季攻略",
        "description": "新赛季更新、奖励获取、活动参与",
        "time": "2026年3月4日"
      },
      {
        "title": "赛季奖励一览",
        "description": "赛季奖励内容、获取难度、奖励分配",
        "time": "2026年3月19日"
      },
      {
        "title": "球员培养攻略",
        "description": "球员升级、技能升级、培养优先级",
        "time": "2026年3月20日"
      },
      {
        "title": "转会市场操作指南",
        "description": "球员购买、出售技巧、市场价格分析",
        "time": "2026年2月27日"
      },
      {
        "title": "训练场使用指南",
        "description": "训练场功能、技能练习、实战演练",
        "time": "2026年3月11日"
      },
      {
        "title": "排位赛上分技巧",
        "description": "排位赛战术、球员搭配、实战技巧",
        "time": "2026年3月8日"
      },
      {
        "title": "进攻战术教学",
        "description": "进攻套路、球员跑位、射门技巧",
        "time": "2026年3月23日"
      },
      {
        "title": "球员开卡欧气展示",
        "description": "开卡过程、稀有球员展示、欧气满满",
        "time": "2026年3月25日"
      },
      {
        "title": "球员卡强化攻略",
        "description": "强化成功率、强化材料、属性提升",
        "time": "2026年3月9日"
      },
      {
        "title": "球员包开箱评测",
        "description": "不同球员包分析、性价比对比、推荐购买",
        "time": "2026年3月16日"
      },
      {
        "title": "俱乐部活动攻略",
        "description": "俱乐部玩法、活动参与、奖励获取",
        "time": "2026年3月4日"
      }
    ]
  },
  "kuaishou": {
    "platform": "快手",
    "items": [
      {
        "title": "球员卡开箱直播",
        "description": "球员包开箱、稀有卡展示、惊喜时刻",
        "time": "2026年3月13日"
      },
      {
        "title": "新手教学直播",
        "description": "基础教学、操作技巧、入门指导",
        "time": "2026年3月9日"
      },
      {
        "title": "转会市场直播",
        "description": "市场操作、球员交易、价格分析",
        "time": "2026年3月6日"
      },
      {
        "title": "球员培养直播",
        "description": "培养过程、升级效果、属性变化",
        "time": "2026年3月20日"
      },
      {
        "title": "球员交易直播",
        "description": "市场交易、球员购买、出售技巧",
        "time": "2026年3月4日"
      },
      {
        "title": "球员数据分析",
        "description": "球员属性、数据对比、强度评估",
        "time": "2026年3月27日"
      },
      {
        "title": "比赛教学直播",
        "description": "比赛教学、技巧演示、实战应用",
        "time": "2026年3月22日"
      },
      {
        "title": "FC足球世界直播",
        "description": "实战直播、球员展示、战术演示",
        "time": "2026年3月11日"
      },
      {
        "title": "UT模式抽卡直播",
        "description": "开卡过程、球员抽取、欧气展示",
        "time": "2026年3月5日"
      },
      {
        "title": "俱乐部管理直播",
        "description": "俱乐部运营、成员管理、活动组织",
        "time": "2026年3月21日"
      },
      {
        "title": "球员对比直播",
        "description": "不同球员对比、优劣分析、选择建议",
        "time": "2026年3月19日"
      },
      {
        "title": "球员推荐直播",
        "description": "球员推荐、性价比分析、适用场景",
        "time": "2026年3月4日"
      },
      {
        "title": "比赛解说直播",
        "description": "比赛解说、战术分析、精彩时刻",
        "time": "2026年3月16日"
      },
      {
        "title": "战术板搭配直播",
        "description": "战术板测试、阵型选择、实战效果",
        "time": "2026年3月6日"
      },
      {
        "title": "比赛实录",
        "description": "比赛回放、精彩集锦、战术分析",
        "time": "2026年3月3日"
      },
      {
        "title": "俱乐部活动直播",
        "description": "俱乐部活动、成员互动、奖励展示",
        "time": "2026年3月7日"
      },
      {
        "title": "赛季活动前瞻",
        "description": "新赛季内容、活动预测、准备建议",
        "time": "2026年3月27日"
      },
      {
        "title": "排位赛直播",
        "description": "排位赛对战、实战技巧、上分过程",
        "time": "2026年3月12日"
      },
      {
        "title": "球员卡升级直播",
        "description": "升级过程、属性提升、材料消耗",
        "time": "2026年3月6日"
      },
      {
        "title": "挑战赛直播",
        "description": "挑战赛挑战、通关技巧、奖励展示",
        "time": "2026年3月22日"
      },
      {
        "title": "游戏版本更新解读",
        "description": "版本更新内容、影响分析、未来展望",
        "time": "2026年3月21日"
      },
      {
        "title": "战术交流直播",
        "description": "战术讨论、阵型分享、球员搭配",
        "time": "2026年3月24日"
      },
      {
        "title": "球员合成直播",
        "description": "合成过程、成功率、球员获取",
        "time": "2026年3月6日"
      },
      {
        "title": "球员卡评测直播",
        "description": "球员卡测试、属性对比、实战表现",
        "time": "2026年3月11日"
      },
      {
        "title": "联赛直播",
        "description": "联赛对战、赛季排名、奖励争夺",
        "time": "2026年3月3日"
      }
    ]
  },
  "bilibili": {
    "platform": "B站",
    "items": [
      {
        "title": "【FC足球世界】球员属性解析",
        "description": "属性详解、关键属性、培养方向",
        "time": "2026年2月26日"
      },
      {
        "title": "【FC足球世界】转会市场攻略",
        "description": "市场分析、操作技巧、交易策略",
        "time": "2026年3月8日"
      },
      {
        "title": "【FC足球世界】赛季奖励攻略",
        "description": "奖励内容、获取难度、奖励分配",
        "time": "2026年2月27日"
      },
      {
        "title": "【FC足球世界】赛季活动攻略",
        "description": "赛季内容、活动参与、奖励获取",
        "time": "2026年3月9日"
      },
      {
        "title": "【FC足球世界】挑战赛攻略",
        "description": "挑战赛详解、通关技巧、奖励分析",
        "time": "2026年3月5日"
      },
      {
        "title": "【FC足球世界】训练场指南",
        "description": "训练场功能、技能练习、实战演练",
        "time": "2026年3月5日"
      },
      {
        "title": "【FC足球世界】俱乐部活动攻略",
        "description": "俱乐部玩法、活动详解、奖励获取",
        "time": "2026年3月24日"
      },
      {
        "title": "【FC足球世界】比赛节奏控制",
        "description": "节奏把握、战术调整、关键时刻",
        "time": "2026年3月3日"
      },
      {
        "title": "【FC足球世界】阵容搭配推荐",
        "description": "阵容搭配、战术配合、球员组合",
        "time": "2026年3月27日"
      },
      {
        "title": "【FC足球世界】排位赛上分攻略",
        "description": "排位赛机制、战术搭配、上分技巧",
        "time": "2026年3月18日"
      },
      {
        "title": "【FC足球世界】球员合成攻略",
        "description": "合成系统、成功率、优质球员",
        "time": "2026年3月21日"
      },
      {
        "title": "【FC足球世界】进攻战术教学",
        "description": "进攻套路、球员跑位、射门技巧",
        "time": "2026年3月15日"
      },
      {
        "title": "【FC足球世界】球员培养指南",
        "description": "培养系统、升级攻略、技能提升",
        "time": "2026年2月26日"
      },
      {
        "title": "【FC足球世界】战术板详解",
        "description": "战术板功能、阵型选择、战术搭配",
        "time": "2026年3月18日"
      },
      {
        "title": "【FC足球世界】球员包评测",
        "description": "球员包分析、性价比对比、推荐购买",
        "time": "2026年3月19日"
      },
      {
        "title": "【FC足球世界】球员交易市场",
        "description": "市场趋势、价格分析、投资建议",
        "time": "2026年3月3日"
      },
      {
        "title": "【攻略】UT模式最强球员推荐",
        "description": "UT模式球员分析、强度排行、推荐列表",
        "time": "2026年3月25日"
      },
      {
        "title": "【FC足球世界】俱乐部运营攻略",
        "description": "俱乐部管理、成员招募、活动组织",
        "time": "2026年2月27日"
      },
      {
        "title": "【FC足球世界】比赛技巧教学",
        "description": "比赛技巧、战术运用、实战演示",
        "time": "2026年3月14日"
      },
      {
        "title": "【FC足球世界】球员强化攻略",
        "description": "强化系统、成功率、属性提升",
        "time": "2026年3月6日"
      },
      {
        "title": "【FC足球世界】新手完全攻略",
        "description": "从零开始、基础教学、快速上手",
        "time": "2026年3月15日"
      },
      {
        "title": "【FC足球世界】特殊球员卡获取",
        "description": "限定卡获取、特殊卡活动、攻略指南",
        "time": "2026年3月22日"
      },
      {
        "title": "【FC足球世界】防守战术详解",
        "description": "防守阵型、球员防守、战术运用",
        "time": "2026年3月26日"
      },
      {
        "title": "【FC足球世界】球员卡评测",
        "description": "球员卡对比、属性分析、实战测试",
        "time": "2026年3月20日"
      },
      {
        "title": "【FC足球世界】球员属性解析",
        "description": "属性详解、关键属性、培养方向",
        "time": "2026年3月15日"
      }
    ]
  },
  "tieba": {
    "platform": "贴吧",
    "items": [
      {
        "title": "【求助】球员应该怎么培养？",
        "description": "培养建议、优先级、属性选择",
        "time": "2026年3月16日"
      },
      {
        "title": "【心得】俱乐部怎么运营？",
        "description": "俱乐部管理、成员招募、活动组织",
        "time": "2026年3月3日"
      },
      {
        "title": "【攻略】战术板怎么设置？",
        "description": "战术板配置、阵型选择、设置技巧",
        "time": "2026年3月18日"
      },
      {
        "title": "【交流】排位赛用什么战术？",
        "description": "战术讨论、阵型推荐、实战经验",
        "time": "2026年3月25日"
      },
      {
        "title": "【交流】转会市场行情",
        "description": "市场价格、趋势分析、交易建议",
        "time": "2026年2月28日"
      },
      {
        "title": "【分享】球员合成成功率",
        "description": "合成经验、成功率、技巧分享",
        "time": "2026年2月26日"
      },
      {
        "title": "【讨论】新赛季有什么活动？",
        "description": "赛季活动、奖励内容、参与方式",
        "time": "2026年3月10日"
      },
      {
        "title": "【分享】比赛精彩时刻",
        "description": "精彩集锦、战术运用、技巧展示",
        "time": "2026年3月5日"
      },
      {
        "title": "【讨论】球员卡哪个属性重要？",
        "description": "属性分析、关键属性、培养方向",
        "time": "2026年3月19日"
      },
      {
        "title": "【讨论】新赛季球员推荐",
        "description": "球员推荐、性价比分析、适用场景",
        "time": "2026年3月16日"
      },
      {
        "title": "【心得】俱乐部活动心得",
        "description": "活动经验、奖励获取、参与建议",
        "time": "2026年3月1日"
      },
      {
        "title": "【分享】球员培养心得",
        "description": "培养经验、属性提升、优化建议",
        "time": "2026年3月18日"
      },
      {
        "title": "【心得】UT模式玩法总结",
        "description": "玩法经验、战术总结、技巧分享",
        "time": "2026年3月24日"
      },
      {
        "title": "【攻略】球员怎么搭配？",
        "description": "球员搭配、阵容组合、战术配合",
        "time": "2026年3月27日"
      },
      {
        "title": "【求助】排位赛怎么上分？",
        "description": "上分技巧、战术选择、实战建议",
        "time": "2026年3月21日"
      },
      {
        "title": "【求助】球员包值得买吗？",
        "description": "球员包分析、性价比、购买建议",
        "time": "2026年3月23日"
      },
      {
        "title": "【讨论】球员卡怎么强化？",
        "description": "强化攻略、材料准备、成功率",
        "time": "2026年2月26日"
      },
      {
        "title": "【攻略】挑战赛怎么通关？",
        "description": "通关技巧、阵容搭配、奖励分析",
        "time": "2026年3月11日"
      },
      {
        "title": "【求助】特殊球员卡怎么获取？",
        "description": "获取途径、活动攻略、获取技巧",
        "time": "2026年3月7日"
      },
      {
        "title": "【交流】比赛节奏怎么控制？",
        "description": "节奏把握、战术调整、经验分享",
        "time": "2026年3月1日"
      },
      {
        "title": "【讨论】UT模式哪个球员最强？",
        "description": "球员强度讨论、玩家推荐、实战体验",
        "time": "2026年3月4日"
      },
      {
        "title": "【交流】阵型选择讨论",
        "description": "阵型分析、优劣对比、选择建议",
        "time": "2026年3月17日"
      },
      {
        "title": "【心得】转会市场怎么操作？",
        "description": "市场操作、交易技巧、价格分析",
        "time": "2026年3月6日"
      },
      {
        "title": "【分享】开卡欧气展示",
        "description": "开卡结果、稀有球员、欧气分享",
        "time": "2026年3月13日"
      },
      {
        "title": "【求助】球员应该怎么培养？",
        "description": "培养建议、优先级、属性选择",
        "time": "2026年3月11日"
      }
    ]
  }
}